nurapi/__about__.py
nurapi/__init__.py
nurapi/bindings.py
nurapi/enums.py
nurapi/helpers.py
nurapi/structures.py
nurapi/lib/linux/libNurApiRaspi.a
nurapi/lib/linux/libNurApiRaspi.so
nurapi/lib/linux/libNurApix64.a
nurapi/lib/linux/libNurApix64.so
nurapi/lib/linux/libNurApix86.a
nurapi/lib/linux/libNurApix86.so
nurapi/lib/windows/arm/NURAPI.dll
nurapi/lib/windows/arm/NURAPI.lib
nurapi/lib/windows/x64/NURAPI.dll
nurapi/lib/windows/x64/NURAPI.lib
nurapi/lib/windows/x86/NURAPI.dll
nurapi/lib/windows/x86/NURAPI.lib
nurapi-1.5.2.dist-info/METADATA
nurapi-1.5.2.dist-info/WHEEL
nurapi-1.5.2.dist-info/licenses/LICENSE.txt
nurapi-1.5.2.dist-info/RECORD
